GCD_Computation/GCD_controller.v
module GCD_controller(ldA,ldB,sel1,sel2,sel_in,done,lt,gt,eq,start,clk);

    input clk,lt,gt,eq,start;
    output reg ldA,ldB,sel1,sel2,sel_in,done;
    reg [2:0] state;
    parameter S0=3'b000,S1=3'b001,S2=3'b010,S3=3'b011,S4=3'b100,S5=3'b101;

    always @(posedge clk)
        begin
            case(state)
                S0:     if(start) state <= S1;
                S1:     state <= S2;
                S2:     #2 if(eq) state <= S5;
                           else if(lt) state <=S3;
                           else state <= S4;
                S3:     #2 if(eq) state <= S5;
                           else if(lt) state <=S3;
                           else state <= S4;
                S4:     #2 if(eq) state <= S5;
                           else if(lt) state <=S3;
                           else state <= S4;
                S5:     state <= S5;
                default: state <=S0;
            endcase
        end

    always @(state)
        begin
            case(state)
                S0: begin
                        sel_in = 1;
                        ldA = 1;
                        ldB = 0;
                        done = 0;
                    end
                S1: begin
                        sel_in = 1;
                        ldA = 0;
                        ldB = 1;
                    end
                S2: if(eq) done = 1;
                    else if(lt) 
                        begin
                            sel1 = 1;
                            sel2 = 0;
                            sel_in = 0;
                            #1 ldA = 0;
                            ldB = 1;
                        end
                    else        
                        begin
                            sel1 = 0;
                            sel2 = 1;
                            sel_in = 0;
                            #1 ldA = 1;
                            ldB = 0;
                        end 
                S3: if(eq) done = 1;
                    else if(lt) 
                        begin
                            sel1 = 1;
                            sel2 = 0;
                            sel_in = 0;
                            #1 ldA = 0;
                            ldB = 1;
                        end
                    else        
                        begin
                            sel1 = 0;
                            sel2 = 1;
                            sel_in = 0;
                            #1 ldA = 1;
                            ldB = 0;
                        end
                S4: if(eq) done = 1;
                    else if(lt) 
                        begin
                            sel1 = 1;
                            sel2 = 0;
                            sel_in = 0;
                            #1 ldA = 0;
                            ldB = 1;
                        end
                    else        
                        begin
                            sel1 = 0;
                            sel2 = 1;
                            sel_in = 0;
                            #1 ldA = 1;
                            ldB = 0;
                        end
                S5: begin
                        done = 1;
                        sel1 = 0;
                        sel2 = 0;
                        ldA = 0;
                        ldB = 0;
                    end
                default:    begin
                                ldA = 0;
                                ldB = 0;
                            end
            endcase
        end

endmodule

GCD_Computation/COMP.v
module COMP(lt,gt,eq,data1,data2);

    input [15:0] data1,data2;
    output lt,gt,eq;

    assign lt = data1 <  data2;
    assign gt = data1 >  data2;
    assign eq = data1 == data2;
    
endmodule

GCD_Computation/SUB.v
module  SUB(out,in1,in2);
    input [15:0] in1,in2;
    output reg [15:0] out;

    always @(*)
        out = in1-in2;

endmodule

GCD_Computation/MUX.v
module MUX(out,in_0,in_1,sel);

    input [15:0] in_0,in_1;
    input sel;
    output [15:0] out;

    assign out = sel ? in_1 : in_0;

endmodule

GCD_Computation/PIPO.v
module PIPO (data_out,data_in,load,clk);

    input [15:0] data_in;
    input load,clk;
    output reg [15:0] data_out;

    always @(posedge clk)
        if(load)    
            data_out <= data_in;    

endmodule

GCD_Computation/GCD_datapath.v
`include "PIPO.v"
`include "COMP.v"
`include "SUB.v"
`include "MUX.v"

module GCD_datapath(gt,lt,eq,ldA,ldB,sel1,sel2,sel_in,data_in,clk);
    
    input ldA,ldB,sel1,sel2,sel_in,clk;
    input [15:0] data_in;
    output lt,gt,eq;
    wire [15:0] X,Y,subOut,Aout,Bout,BUS;

    PIPO    A (Aout,BUS,ldA,clk);
    PIPO    B (Bout,BUS,ldB,clk);
    MUX     M1 (X,Aout,Bout,sel1);
    MUX     M2 (Y,Aout,Bout,sel2);
    MUX     M_data (BUS,subOut,data_in,sel_in);
    SUB     S (subOut,X,Y);
    COMP    C (lt,gt,eq,Aout,Bout);

endmodule

GCD_Computation/tb_GCD.v
`include "GCD_datapath.v"
`include "GCD_controller.v"

module tb_GCD;
    reg [15:0] data_in;
    reg clk,start;
    wire done;

    reg [15:0] A,B;

    GCD_datapath DP (gt,lt,eq,ldA,ldB,sel1,sel2,sel_in,data_in,clk);
    GCD_controller CTRL (ldA,ldB,sel1,sel2,sel_in,done,lt,gt,eq,start,clk);

    initial
    begin
        clk = 1'b0;
        #3 start = 1'b1;
        #1000 $finish; 
    end
    
    always #5 clk = ~clk;

    initial
    begin
        #12 data_in = 143;
        #10 data_in = 78;
    end 

    initial
    begin
        $monitor ($time, " %d %b ",DP.Aout,done);
        $dumpfile ("GCD.vcd");
        $dumpvars (0, tb_GCD);
    end

endmodule

GCD_Computation/GCD.vcd
$date
	Fri May 31 22:26:41 2019
$end
$version
	Icarus Verilog
$end
$timescale
	1s
$end
$scope module tb_GCD $end
$var wire 1 ! sel_in $end
$var wire 1 " sel2 $end
$var wire 1 # sel1 $end
$var wire 1 $ lt $end
$var wire 1 % ldB $end
$var wire 1 & ldA $end
$var wire 1 ' gt $end
$var wire 1 ( eq $end
$var wire 1 ) done $end
$var reg 1 * clk $end
$var reg 16 + data_in [15:0] $end
$var reg 1 , start $end
$scope module CTRL $end
$var wire 1 * clk $end
$var wire 1 , start $end
$var wire 1 $ lt $end
$var wire 1 ' gt $end
$var wire 1 ( eq $end
$var reg 1 ) done $end
$var reg 1 & ldA $end
$var reg 1 % ldB $end
$var reg 1 # sel1 $end
$var reg 1 " sel2 $end
$var reg 1 ! sel_in $end
$var reg 3 - state [2:0] $end
$upscope $end
$scope module DP $end
$var wire 1 * clk $end
$var wire 16 . data_in [15:0] $end
$var wire 1 & ldA $end
$var wire 1 % ldB $end
$var wire 1 # sel1 $end
$var wire 1 " sel2 $end
$var wire 1 ! sel_in $end
$var wire 16 / subOut [15:0] $end
$var wire 1 $ lt $end
$var wire 1 ' gt $end
$var wire 1 ( eq $end
$var wire 16 0 Y [15:0] $end
$var wire 16 1 X [15:0] $end
$var wire 16 2 Bout [15:0] $end
$var wire 16 3 BUS [15:0] $end
$var wire 16 4 Aout [15:0] $end
$scope module A $end
$var wire 1 * clk $end
$var wire 1 & load $end
$var wire 16 5 data_in [15:0] $end
$var reg 16 6 data_out [15:0] $end
$upscope $end
$scope module B $end
$var wire 1 * clk $end
$var wire 1 % load $end
$var wire 16 7 data_in [15:0] $end
$var reg 16 8 data_out [15:0] $end
$upscope $end
$scope module C $end
$var wire 16 9 data1 [15:0] $end
$var wire 16 : data2 [15:0] $end
$var wire 1 $ lt $end
$var wire 1 ' gt $end
$var wire 1 ( eq $end
$upscope $end
$scope module M1 $end
$var wire 16 ; in_0 [15:0] $end
$var wire 16 < in_1 [15:0] $end
$var wire 1 # sel $end
$var wire 16 = out [15:0] $end
$upscope $end
$scope module M2 $end
$var wire 16 > in_0 [15:0] $end
$var wire 16 ? in_1 [15:0] $end
$var wire 1 " sel $end
$var wire 16 @ out [15:0] $end
$upscope $end
$scope module M_data $end
$var wire 16 A in_1 [15:0] $end
$var wire 1 ! sel $end
$var wire 16 B out [15:0] $end
$var wire 16 C in_0 [15:0] $end
$upscope $end
$scope module S $end
$var wire 16 D in1 [15:0] $end
$var wire 16 E in2 [15:0] $end
$var reg 16 F out [15:0] $end
$upscope $end
$upscope $end
$upscope $end
$enddefinitions $end
#0
$dumpvars
bx F
bx E
bx D
bx C
bx B
bx A
bx @
bx ?
bx >
bx =
bx <
bx ;
bx :
bx 9
bx 8
bx 7
bx 6
bx 5
bx 4
bx 3
bx 2
bx 1
bx 0
bx /
bx .
bx -
x,
bx +
0*
x)
x(
x'
x&
x%
x$
x#
x"
x!
$end
#3
1,
#5
0)
0%
1&
1!
b0 -
1*
#10
0*
#12
b10001111 3
b10001111 5
b10001111 7
b10001111 B
b10001111 +
b10001111 .
b10001111 A
#15
1%
0&
b1 -
b10001111 4
b10001111 6
b10001111 9
b10001111 ;
b10001111 >
1*
#20
0*
#22
b1001110 3
b1001110 5
b1001110 7
b1001110 B
b1001110 +
b1001110 .
b1001110 A
#25
b1000001 /
b1000001 C
b1000001 F
b1000001 3
b1000001 5
b1000001 7
b1000001 B
b10001111 1
b10001111 =
b10001111 D
b1001110 0
b1001110 @
b1001110 E
0!
1"
0#
0$
1'
0(
b1001110 2
b1001110 8
b1001110 :
b1001110 <
b1001110 ?
b10 -
1*
#26
0%
1&
#30
0*
#35
b1111111111110011 3
b1111111111110011 5
b1111111111110011 7
b1111111111110011 B
b1111111111110011 /
b1111111111110011 C
b1111111111110011 F
b1000001 1
b1000001 =
b1000001 D
1$
0'
b1000001 4
b1000001 6
b1000001 9
b1000001 ;
b1000001 >
1*
#37
b1101 3
b1101 5
b1101 7
b1101 B
b1101 /
b1101 C
b1101 F
b1000001 0
b1000001 @
b1000001 E
b1001110 1
b1001110 =
b1001110 D
0"
1#
b11 -
#38
1%
0&
#40
0*
#45
b1111111111001100 3
b1111111111001100 5
b1111111111001100 7
b1111111111001100 B
b1111111111001100 /
b1111111111001100 C
b1111111111001100 F
b1101 1
b1101 =
b1101 D
0$
1'
b1101 2
b1101 8
b1101 :
b1101 <
b1101 ?
1*
#47
b110100 3
b110100 5
b110100 7
b110100 B
b110100 /
b110100 C
b110100 F
b1101 0
b1101 @
b1101 E
b1000001 1
b1000001 =
b1000001 D
1"
0#
b100 -
#48
0%
1&
#50
0*
#55
b100111 3
b100111 5
b100111 7
b100111 B
b100111 /
b100111 C
b100111 F
b110100 1
b110100 =
b110100 D
b110100 4
b110100 6
b110100 9
b110100 ;
b110100 >
1*
#60
0*
#65
b11010 3
b11010 5
b11010 7
b11010 B
b11010 /
b11010 C
b11010 F
b100111 1
b100111 =
b100111 D
b100111 4
b100111 6
b100111 9
b100111 ;
b100111 >
1*
#70
0*
#75
b1101 3
b1101 5
b1101 7
b1101 B
b1101 /
b1101 C
b1101 F
b11010 1
b11010 =
b11010 D
b11010 4
b11010 6
b11010 9
b11010 ;
b11010 >
1*
#80
0*
#85
b0 3
b0 5
b0 7
b0 B
b0 /
b0 C
b0 F
b1101 1
b1101 =
b1101 D
0'
1(
b1101 4
b1101 6
b1101 9
b1101 ;
b1101 >
1*
#87
0&
0"
1)
b101 -
